[
  {
    "name": "Alchemist",
    "startingWeapon": {
      "meleeDamage": "1d4",
      "wield": "ONE_HANDED",
      "type": "MELEE",
      "notes": [],
      "name": "Staff",
      "costInCopper": 50.0
    },
    "tradeGood": {
      "notes": [
        "***When ignited and tossed, inflicts 1d6 damage + fire.",
        "A flask of oil burns for six hours in a lantern."
      ],
      "name": "Oil, 1 flask***",
      "costInCopper": 20.0
    }
  },
  {
    "name": "Animal trainer",
    "startingWeapon": {
      "meleeDamage": "1d4",
      "wield": "ONE_HANDED",
      "type": "MELEE",
      "notes": [],
      "name": "Club",
      "costInCopper": 300.0
    },
    "tradeGood": {
      "notes": [],
      "name": "Pony",
      "costInCopper": 3000.0
    }
  },
  {
    "name": "Armorer",
    "startingWeapon": {
      "meleeDamage": "1d4",
      "wield": "ONE_HANDED",
      "type": "MELEE",
      "notes": [],
      "name": "Hammer (as club)",
      "costInCopper": 300.0
    },
    "tradeGood": {
      "name": "Iron helmet",
      "costInCopper": 0.0
    }
  },
  {
    "name": "Astrologer",
    "startingWeapon": {
      "meleeDamage": "1d4",
      "rangedDamage": "1d10",
      "range": "10/20/30**",
      "wield": "ONE_HANDED",
      "type": "BOTH",
      "notes": [
        "† Thieves, when backstabbing, use the 2nd damage value, all others use the 1st.",
        "‡Chaotic chars use ceremonial daggers known as Athame, Kris, or Tumi.",
        "**Strength mod applies to damage at close range only."
      ],
      "name": "Dagger†‡",
      "costInCopper": 300.0
    },
    "tradeGood": {
      "name": "Spyglass",
      "costInCopper": 0.0
    }
  },
  {
    "name": "Barber",
    "startingWeapon": {
      "meleeDamage": "1d4",
      "rangedDamage": "1d10",
      "range": "10/20/30**",
      "wield": "ONE_HANDED",
      "type": "BOTH",
      "notes": [
        "† Thieves, when backstabbing, use the 2nd damage value, all others use the 1st.",
        "‡Chaotic chars use ceremonial daggers known as Athame, Kris, or Tumi.",
        "**Strength mod applies to damage at close range only."
      ],
      "name": "Razor (as dagger)",
      "costInCopper": 300.0
    },
    "tradeGood": {
      "name": "Scissors",
      "costInCopper": 0.0
    }
  },
  {
    "name": "Beadle",
    "startingWeapon": {
      "meleeDamage": "1d4",
      "wield": "ONE_HANDED",
      "type": "MELEE",
      "notes": [],
      "name": "Staff",
      "costInCopper": 50.0
    },
    "tradeGood": {
      "notes": [],
      "name": "Holy symbol",
      "costInCopper": 2500.0
    }
  },
  {
    "name": "Beekeeper",
    "startingWeapon": {
      "meleeDamage": "1d4",
      "wield": "ONE_HANDED",
      "type": "MELEE",
      "notes": [],
      "name": "Staff",
      "costInCopper": 50.0
    },
    "tradeGood": {
      "name": "Jar of honey",
      "costInCopper": 0.0
    }
  },
  {
    "name": "Blacksmith",
    "startingWeapon": {
      "meleeDamage": "1d4",
      "wield": "ONE_HANDED",
      "type": "MELEE",
      "notes": [],
      "name": "Hammer (as club)",
      "costInCopper": 300.0
    },
    "tradeGood": {
      "name": "Steel tongs",
      "costInCopper": 0.0
    }
  },
  {
    "name": "Butcher",
    "startingWeapon": {
      "meleeDamage": "1d6",
      "rangedDamage": "1d6",
      "range": "10/20/30**",
      "wield": "ONE_HANDED",
      "type": "BOTH",
      "notes": [
        "**Strength mod applies to damage at close range only."
      ],
      "name": "Cleaver (as axe)",
      "costInCopper": 400.0
    },
    "tradeGood": {
      "name": "Side of beef",
      "costInCopper": 0.0
    }
  },
  {
    "name": "Caravan guard",
    "startingWeapon": {
      "meleeDamage": "1d6",
      "wield": "ONE_HANDED",
      "type": "MELEE",
      "notes": [],
      "name": "Short sword",
      "costInCopper": 700.0
    },
    "tradeGood": {
      "name": "Linen, 1 yard",
      "costInCopper": 0.0
    }
  },
  {
    "name": "Cheesemaker",
    "startingWeapon": {
      "meleeDamage": "1d4",
      "wield": "ONE_HANDED",
      "type": "MELEE",
      "notes": [],
      "name": "Cudgel (as staff)",
      "costInCopper": 50.0
    },
    "tradeGood": {
      "name": "Stinky cheese",
      "costInCopper": 0.0
    }
  },
  {
    "name": "Cobbler",
    "startingWeapon": {
      "meleeDamage": "1d4",
      "rangedDamage": "1d10",
      "range": "10/20/30**",
      "wield": "ONE_HANDED",
      "type": "BOTH",
      "notes": [
        "† Thieves, when backstabbing, use the 2nd damage value, all others use the 1st.",
        "‡Chaotic chars use ceremonial daggers known as Athame, Kris, or Tumi.",
        "**Strength mod applies to damage at close range only."
      ],
      "name": "Awl (as dagger)",
      "costInCopper": 300.0
    },
    "tradeGood": {
      "name": "Shoehorn",
      "costInCopper": 0.0
    }
  },
  {
    "name": "Confidence artist",
    "startingWeapon": {
      "meleeDamage": "1d4",
      "rangedDamage": "1d10",
      "range": "10/20/30**",
      "wield": "ONE_HANDED",
      "type": "BOTH",
      "notes": [
        "† Thieves, when backstabbing, use the 2nd damage value, all others use the 1st.",
        "‡Chaotic chars use ceremonial daggers known as Athame, Kris, or Tumi.",
        "**Strength mod applies to damage at close range only."
      ],
      "name": "Dagger†‡",
      "costInCopper": 300.0
    },
    "tradeGood": {
      "name": "Quality cloak",
      "costInCopper": 0.0
    }
  },
  {
    "name": "Cooper",
    "startingWeapon": {
      "meleeDamage": "1d4",
      "wield": "ONE_HANDED",
      "type": "MELEE",
      "notes": [],
      "name": "Crowbar (as club)",
      "costInCopper": 300.0
    },
    "tradeGood": {
      "name": "Barrel",
      "costInCopper": 0.0
    }
  },
  {
    "name": "Costermonger",
    "startingWeapon": {
      "meleeDamage": "1d4",
      "rangedDamage": "1d10",
      "range": "10/20/30**",
      "wield": "ONE_HANDED",
      "type": "BOTH",
      "notes": [
        "† Thieves, when backstabbing, use the 2nd damage value, all others use the 1st.",
        "‡Chaotic chars use ceremonial daggers known as Athame, Kris, or Tumi.",
        "**Strength mod applies to damage at close range only."
      ],
      "name": "Knife (as dagger)",
      "costInCopper": 300.0
    },
    "tradeGood": {
      "name": "Fruit",
      "costInCopper": 0.0
    }
  },
  {
    "name": "Cutpurse",
    "startingWeapon": {
      "meleeDamage": "1d4",
      "rangedDamage": "1d10",
      "range": "10/20/30**",
      "wield": "ONE_HANDED",
      "type": "BOTH",
      "notes": [
        "† Thieves, when backstabbing, use the 2nd damage value, all others use the 1st.",
        "‡Chaotic chars use ceremonial daggers known as Athame, Kris, or Tumi.",
        "**Strength mod applies to damage at close range only."
      ],
      "name": "Dagger†‡",
      "costInCopper": 300.0
    },
    "tradeGood": {
      "name": "Small chest",
      "costInCopper": 0.0
    }
  },
  {
    "name": "Ditch digger",
    "startingWeapon": {
      "meleeDamage": "1d4",
      "wield": "ONE_HANDED",
      "type": "MELEE",
      "notes": [],
      "name": "Shovel (as staff)",
      "costInCopper": 50.0
    },
    "tradeGood": {
      "name": "Fine dirt, 1 lb.",
      "costInCopper": 0.0
    }
  },
  {
    "name": "Dock worker",
    "startingWeapon": {
      "meleeDamage": "1d4",
      "wield": "ONE_HANDED",
      "type": "MELEE",
      "notes": [],
      "name": "Pole (as staff)",
      "costInCopper": 50.0
    },
    "tradeGood": {
      "name": "1 late RPG book",
      "costInCopper": 0.0
    }
  },
  {
    "name": "Dwarven apothecarist",
    "startingWeapon": {
      "meleeDamage": "1d4",
      "wield": "ONE_HANDED",
      "type": "MELEE",
      "notes": [],
      "name": "Cudgel (as staff)",
      "costInCopper": 50.0
    },
    "tradeGood": {
      "name": "Steel vial",
      "costInCopper": 0.0
    }
  },
  {
    "name": "Dwarven blacksmith",
    "startingWeapon": {
      "meleeDamage": "1d4",
      "wield": "ONE_HANDED",
      "type": "MELEE",
      "notes": [],
      "name": "Hammer (as club)",
      "costInCopper": 300.0
    },
    "tradeGood": {
      "name": "Mithril, 1 oz.",
      "costInCopper": 0.0
    }
  },
  {
    "name": "Dwarven chest maker",
    "startingWeapon": {
      "meleeDamage": "1d4",
      "rangedDamage": "1d10",
      "range": "10/20/30**",
      "wield": "ONE_HANDED",
      "type": "BOTH",
      "notes": [
        "† Thieves, when backstabbing, use the 2nd damage value, all others use the 1st.",
        "‡Chaotic chars use ceremonial daggers known as Athame, Kris, or Tumi.",
        "**Strength mod applies to damage at close range only."
      ],
      "name": "Chisel (as dagger)",
      "costInCopper": 300.0
    },
    "tradeGood": {
      "name": "Wood, 10 lbs.",
      "costInCopper": 0.0
    }
  },
  {
    "name": "Dwarven herder",
    "startingWeapon": {
      "meleeDamage": "1d4",
      "wield": "ONE_HANDED",
      "type": "MELEE",
      "notes": [],
      "name": "Staff",
      "costInCopper": 50.0
    }
  },
  {
    "name": "Dwarven miner",
    "startingWeapon": {
      "meleeDamage": "1d4",
      "wield": "ONE_HANDED",
      "type": "MELEE",
      "notes": [],
      "name": "Pick (as club)",
      "costInCopper": 300.0
    },
    "tradeGood": {
      "notes": [],
      "name": "Lantern",
      "costInCopper": 1000.0
    }
  },
  {
    "name": "Dwarven mushroom farmer",
    "startingWeapon": {
      "meleeDamage": "1d4",
      "wield": "ONE_HANDED",
      "type": "MELEE",
      "notes": [],
      "name": "Shovel (as staff)",
      "costInCopper": 50.0
    },
    "tradeGood": {
      "name": "Sack",
      "costInCopper": 0.0
    }
  },
  {
    "name": "Dwarven rat catcher",
    "startingWeapon": {
      "meleeDamage": "1d4",
      "wield": "ONE_HANDED",
      "type": "MELEE",
      "notes": [],
      "name": "Club",
      "costInCopper": 300.0
    },
    "tradeGood": {
      "name": "Net",
      "costInCopper": 0.0
    }
  },
  {
    "name": "Dwarven stonemason",
    "startingWeapon": {
      "meleeDamage": "1d4",
      "wield": "ONE_HANDED",
      "type": "MELEE",
      "notes": [],
      "name": "Hammer (as club)",
      "costInCopper": 300.0
    },
    "tradeGood": {
      "name": "Fine stone, 10 lbs.",
      "costInCopper": 0.0
    }
  },
  {
    "name": "Elven artisan",
    "startingWeapon": {
      "meleeDamage": "1d4",
      "wield": "ONE_HANDED",
      "type": "MELEE",
      "notes": [],
      "name": "Staff",
      "costInCopper": 50.0
    },
    "tradeGood": {
      "name": "Clay, 1 lb.",
      "costInCopper": 0.0
    }
  },
  {
    "name": "Elven barrister",
    "startingWeapon": {
      "range": "20/40/60**",
      "rangedDamage": "1d4",
      "wield": "ONE_HANDED",
      "type": "RANGED",
      "notes": [
        "**Strength mod applies to damage at close range only."
      ],
      "name": "Quill (as dart)",
      "costInCopper": 50.0
    },
    "tradeGood": {
      "name": "Book",
      "costInCopper": 0.0
    }
  },
  {
    "name": "Elven chandler",
    "startingWeapon": {
      "meleeDamage": "1d4",
      "rangedDamage": "1d10",
      "range": "10/20/30**",
      "wield": "ONE_HANDED",
      "type": "BOTH",
      "notes": [
        "† Thieves, when backstabbing, use the 2nd damage value, all others use the 1st.",
        "‡Chaotic chars use ceremonial daggers known as Athame, Kris, or Tumi.",
        "**Strength mod applies to damage at close range only."
      ],
      "name": "Scissors (as dagger)",
      "costInCopper": 300.0
    },
    "tradeGood": {
      "name": "Candles, 20",
      "costInCopper": 0.0
    }
  },
  {
    "name": "Elven falconer",
    "startingWeapon": {
      "meleeDamage": "1d4",
      "rangedDamage": "1d10",
      "range": "10/20/30**",
      "wield": "ONE_HANDED",
      "type": "BOTH",
      "notes": [
        "† Thieves, when backstabbing, use the 2nd damage value, all others use the 1st.",
        "‡Chaotic chars use ceremonial daggers known as Athame, Kris, or Tumi.",
        "**Strength mod applies to damage at close range only."
      ],
      "name": "Dagger†‡",
      "costInCopper": 300.0
    },
    "tradeGood": {
      "name": "Falcon",
      "costInCopper": 0.0
    }
  },
  {
    "name": "Elven forester",
    "startingWeapon": {
      "meleeDamage": "1d4",
      "wield": "ONE_HANDED",
      "type": "MELEE",
      "notes": [],
      "name": "Staff",
      "costInCopper": 50.0
    },
    "tradeGood": {
      "name": "Herbs, 1 lb.",
      "costInCopper": 0.0
    }
  },
  {
    "name": "Elven glassblower",
    "startingWeapon": {
      "meleeDamage": "1d4",
      "wield": "ONE_HANDED",
      "type": "MELEE",
      "notes": [],
      "name": "Hammer (as club)",
      "costInCopper": 300.0
    },
    "tradeGood": {
      "name": "Glass beads",
      "costInCopper": 0.0
    }
  },
  {
    "name": "Elven navigator",
    "startingWeapon": {
      "range": "50/100/150",
      "rangedDamage": "1d6",
      "wield": "TWO_HANDED",
      "type": "RANGED",
      "notes": [
        "*Two-handed weapons use a d16 on initiative checks."
      ],
      "name": "Shortbow",
      "costInCopper": 2500.0
    },
    "tradeGood": {
      "name": "Spyglass",
      "costInCopper": 0.0
    }
  },
  {
    "name": "Elven sage",
    "startingWeapon": {
      "meleeDamage": "1d4",
      "rangedDamage": "1d10",
      "range": "10/20/30**",
      "wield": "ONE_HANDED",
      "type": "BOTH",
      "notes": [
        "† Thieves, when backstabbing, use the 2nd damage value, all others use the 1st.",
        "‡Chaotic chars use ceremonial daggers known as Athame, Kris, or Tumi.",
        "**Strength mod applies to damage at close range only."
      ],
      "name": "Dagger†‡",
      "costInCopper": 300.0
    },
    "tradeGood": {
      "name": "Parchment and quill pen",
      "costInCopper": 0.0
    }
  },
  {
    "name": "Farmer",
    "startingWeapon": {
      "meleeDamage": "1d8",
      "wield": "ONE_HANDED",
      "type": "MELEE",
      "notes": [
        "#These weapons inflict 2x damage on a mounted charge."
      ],
      "name": "Pitchfork (as spear)",
      "costInCopper": 300.0
    }
  },
  {
    "name": "Fortune-teller",
    "startingWeapon": {
      "meleeDamage": "1d4",
      "rangedDamage": "1d10",
      "range": "10/20/30**",
      "wield": "ONE_HANDED",
      "type": "BOTH",
      "notes": [
        "† Thieves, when backstabbing, use the 2nd damage value, all others use the 1st.",
        "‡Chaotic chars use ceremonial daggers known as Athame, Kris, or Tumi.",
        "**Strength mod applies to damage at close range only."
      ],
      "name": "Dagger†‡",
      "costInCopper": 300.0
    },
    "tradeGood": {
      "name": "Tarot deck",
      "costInCopper": 0.0
    }
  },
  {
    "name": "Gambler",
    "startingWeapon": {
      "meleeDamage": "1d4",
      "wield": "ONE_HANDED",
      "type": "MELEE",
      "notes": [],
      "name": "Club",
      "costInCopper": 300.0
    },
    "tradeGood": {
      "name": "Dice",
      "costInCopper": 0.0
    }
  },
  {
    "name": "Gongfarmer",
    "startingWeapon": {
      "meleeDamage": "1d4",
      "rangedDamage": "1d10",
      "range": "10/20/30**",
      "wield": "ONE_HANDED",
      "type": "BOTH",
      "notes": [
        "† Thieves, when backstabbing, use the 2nd damage value, all others use the 1st.",
        "‡Chaotic chars use ceremonial daggers known as Athame, Kris, or Tumi.",
        "**Strength mod applies to damage at close range only."
      ],
      "name": "Dagger†‡",
      "costInCopper": 300.0
    },
    "tradeGood": {
      "name": "Sack of night soil",
      "costInCopper": 0.0
    }
  },
  {
    "name": "Grave digger",
    "startingWeapon": {
      "meleeDamage": "1d4",
      "wield": "ONE_HANDED",
      "type": "MELEE",
      "notes": [],
      "name": "Shovel (as staff)",
      "costInCopper": 50.0
    },
    "tradeGood": {
      "name": "Trowel",
      "costInCopper": 0.0
    }
  },
  {
    "name": "Guild beggar",
    "startingWeapon": {
      "range": "40/80/160**",
      "rangedDamage": "1d4",
      "wield": "ONE_HANDED",
      "type": "RANGED",
      "notes": [
        "**Strength mod applies to damage at close range only."
      ],
      "name": "Sling",
      "costInCopper": 200.0
    },
    "tradeGood": {
      "name": "Crutches",
      "costInCopper": 0.0
    }
  },
  {
    "name": "Halfling chicken butcher",
    "startingWeapon": {
      "meleeDamage": "1d6",
      "rangedDamage": "1d6",
      "range": "10/20/30**",
      "wield": "ONE_HANDED",
      "type": "BOTH",
      "notes": [
        "**Strength mod applies to damage at close range only."
      ],
      "name": "Handaxe",
      "costInCopper": 400.0
    },
    "tradeGood": {
      "name": "Chicken meat, 5 lbs.",
      "costInCopper": 0.0
    }
  },
  {
    "name": "Halfling dyer",
    "startingWeapon": {
      "meleeDamage": "1d4",
      "wield": "ONE_HANDED",
      "type": "MELEE",
      "notes": [],
      "name": "Staff",
      "costInCopper": 50.0
    },
    "tradeGood": {
      "name": "Fabric, 3 yards",
      "costInCopper": 0.0
    }
  },
  {
    "name": "Halfling glovemaker",
    "startingWeapon": {
      "meleeDamage": "1d4",
      "rangedDamage": "1d10",
      "range": "10/20/30**",
      "wield": "ONE_HANDED",
      "type": "BOTH",
      "notes": [
        "† Thieves, when backstabbing, use the 2nd damage value, all others use the 1st.",
        "‡Chaotic chars use ceremonial daggers known as Athame, Kris, or Tumi.",
        "**Strength mod applies to damage at close range only."
      ],
      "name": "Awl (as dagger)",
      "costInCopper": 300.0
    },
    "tradeGood": {
      "name": "Gloves, 4 pair",
      "costInCopper": 0.0
    }
  },
  {
    "name": "Halfling gypsy",
    "startingWeapon": {
      "range": "40/80/160**",
      "rangedDamage": "1d4",
      "wield": "ONE_HANDED",
      "type": "RANGED",
      "notes": [
        "**Strength mod applies to damage at close range only."
      ],
      "name": "Sling",
      "costInCopper": 200.0
    },
    "tradeGood": {
      "name": "Hex doll",
      "costInCopper": 0.0
    }
  },
  {
    "name": "Halfling haberdasher",
    "startingWeapon": {
      "meleeDamage": "1d4",
      "rangedDamage": "1d10",
      "range": "10/20/30**",
      "wield": "ONE_HANDED",
      "type": "BOTH",
      "notes": [
        "† Thieves, when backstabbing, use the 2nd damage value, all others use the 1st.",
        "‡Chaotic chars use ceremonial daggers known as Athame, Kris, or Tumi.",
        "**Strength mod applies to damage at close range only."
      ],
      "name": "Scissors (as dagger)",
      "costInCopper": 300.0
    },
    "tradeGood": {
      "name": "Fine suits, 3 sets",
      "costInCopper": 0.0
    }
  },
  {
    "name": "Halfling mariner",
    "startingWeapon": {
      "meleeDamage": "1d4",
      "rangedDamage": "1d10",
      "range": "10/20/30**",
      "wield": "ONE_HANDED",
      "type": "BOTH",
      "notes": [
        "† Thieves, when backstabbing, use the 2nd damage value, all others use the 1st.",
        "‡Chaotic chars use ceremonial daggers known as Athame, Kris, or Tumi.",
        "**Strength mod applies to damage at close range only."
      ],
      "name": "Knife (as dagger)",
      "costInCopper": 300.0
    },
    "tradeGood": {
      "name": "Sailcloth, 2 yards",
      "costInCopper": 0.0
    }
  },
  {
    "name": "Halfling moneylender",
    "startingWeapon": {
      "meleeDamage": "1d6",
      "wield": "ONE_HANDED",
      "type": "MELEE",
      "notes": [],
      "name": "Short sword",
      "costInCopper": 700.0
    },
    "tradeGood": {
      "name": "5GP, 10SP, 200CP",
      "costInCopper": 0.0
    }
  },
  {
    "name": "Halfling trader",
    "startingWeapon": {
      "meleeDamage": "1d6",
      "wield": "ONE_HANDED",
      "type": "MELEE",
      "notes": [],
      "name": "Short sword",
      "costInCopper": 700.0
    },
    "tradeGood": {
      "name": "20SP",
      "costInCopper": 0.0
    }
  },
  {
    "name": "Halfling vagrant",
    "startingWeapon": {
      "meleeDamage": "1d4",
      "wield": "ONE_HANDED",
      "type": "MELEE",
      "notes": [],
      "name": "Club",
      "costInCopper": 300.0
    },
    "tradeGood": {
      "name": "Begging bowl",
      "costInCopper": 0.0
    }
  },
  {
    "name": "Healer",
    "startingWeapon": {
      "meleeDamage": "1d4",
      "wield": "ONE_HANDED",
      "type": "MELEE",
      "notes": [],
      "name": "Club",
      "costInCopper": 300.0
    },
    "tradeGood": {
      "notes": [],
      "name": "Holy symbol",
      "costInCopper": 2500.0
    }
  },
  {
    "name": "Herbalist",
    "startingWeapon": {
      "meleeDamage": "1d4",
      "wield": "ONE_HANDED",
      "type": "MELEE",
      "notes": [],
      "name": "Club",
      "costInCopper": 300.0
    },
    "tradeGood": {
      "name": "Herbs, 1 lb.",
      "costInCopper": 0.0
    }
  },
  {
    "name": "Herder",
    "startingWeapon": {
      "meleeDamage": "1d4",
      "wield": "ONE_HANDED",
      "type": "MELEE",
      "notes": [],
      "name": "Staff",
      "costInCopper": 50.0
    }
  },
  {
    "name": "Hunter",
    "startingWeapon": {
      "range": "50/100/150",
      "rangedDamage": "1d6",
      "wield": "TWO_HANDED",
      "type": "RANGED",
      "notes": [
        "*Two-handed weapons use a d16 on initiative checks."
      ],
      "name": "Shortbow",
      "costInCopper": 2500.0
    },
    "tradeGood": {
      "name": "Deer pelt",
      "costInCopper": 0.0
    }
  },
  {
    "name": "Indentured servant",
    "startingWeapon": {
      "meleeDamage": "1d4",
      "wield": "ONE_HANDED",
      "type": "MELEE",
      "notes": [],
      "name": "Staff",
      "costInCopper": 50.0
    },
    "tradeGood": {
      "name": "Locket",
      "costInCopper": 0.0
    }
  },
  {
    "name": "Jester",
    "startingWeapon": {
      "range": "20/40/60**",
      "rangedDamage": "1d4",
      "wield": "ONE_HANDED",
      "type": "RANGED",
      "notes": [
        "**Strength mod applies to damage at close range only."
      ],
      "name": "Dart",
      "costInCopper": 50.0
    },
    "tradeGood": {
      "name": "Silk clothes",
      "costInCopper": 0.0
    }
  },
  {
    "name": "Jeweler",
    "startingWeapon": {
      "meleeDamage": "1d4",
      "rangedDamage": "1d10",
      "range": "10/20/30**",
      "wield": "ONE_HANDED",
      "type": "BOTH",
      "notes": [
        "† Thieves, when backstabbing, use the 2nd damage value, all others use the 1st.",
        "‡Chaotic chars use ceremonial daggers known as Athame, Kris, or Tumi.",
        "**Strength mod applies to damage at close range only."
      ],
      "name": "Dagger†‡",
      "costInCopper": 300.0
    },
    "tradeGood": {
      "name": "Gem worth 20GP",
      "costInCopper": 0.0
    }
  },
  {
    "name": "Locksmith",
    "startingWeapon": {
      "meleeDamage": "1d4",
      "rangedDamage": "1d10",
      "range": "10/20/30**",
      "wield": "ONE_HANDED",
      "type": "BOTH",
      "notes": [
        "† Thieves, when backstabbing, use the 2nd damage value, all others use the 1st.",
        "‡Chaotic chars use ceremonial daggers known as Athame, Kris, or Tumi.",
        "**Strength mod applies to damage at close range only."
      ],
      "name": "Dagger†‡",
      "costInCopper": 300.0
    },
    "tradeGood": {
      "name": "Fine tools",
      "costInCopper": 0.0
    }
  },
  {
    "name": "Mendicant",
    "startingWeapon": {
      "meleeDamage": "1d4",
      "wield": "ONE_HANDED",
      "type": "MELEE",
      "notes": [],
      "name": "Club",
      "costInCopper": 300.0
    },
    "tradeGood": {
      "name": "Cheese dip",
      "costInCopper": 0.0
    }
  },
  {
    "name": "Mercenary",
    "startingWeapon": {
      "meleeDamage": "1d8",
      "wield": "ONE_HANDED",
      "type": "MELEE",
      "notes": [],
      "name": "Longsword",
      "costInCopper": 1000.0
    },
    "tradeGood": {
      "name": "Hide armor (equipped)",
      "costInCopper": 0.0
    }
  },
  {
    "name": "Merchant",
    "startingWeapon": {
      "meleeDamage": "1d4",
      "rangedDamage": "1d10",
      "range": "10/20/30**",
      "wield": "ONE_HANDED",
      "type": "BOTH",
      "notes": [
        "† Thieves, when backstabbing, use the 2nd damage value, all others use the 1st.",
        "‡Chaotic chars use ceremonial daggers known as Athame, Kris, or Tumi.",
        "**Strength mod applies to damage at close range only."
      ],
      "name": "Dagger†‡",
      "costInCopper": 300.0
    },
    "tradeGood": {
      "name": "4GP, 14SP, 27CP",
      "costInCopper": 0.0
    }
  },
  {
    "name": "Miller/baker",
    "startingWeapon": {
      "meleeDamage": "1d4",
      "wield": "ONE_HANDED",
      "type": "MELEE",
      "notes": [],
      "name": "Club",
      "costInCopper": 300.0
    },
    "tradeGood": {
      "name": "Flour, 1 lb.",
      "costInCopper": 0.0
    }
  },
  {
    "name": "Minstrel",
    "startingWeapon": {
      "meleeDamage": "1d4",
      "rangedDamage": "1d10",
      "range": "10/20/30**",
      "wield": "ONE_HANDED",
      "type": "BOTH",
      "notes": [
        "† Thieves, when backstabbing, use the 2nd damage value, all others use the 1st.",
        "‡Chaotic chars use ceremonial daggers known as Athame, Kris, or Tumi.",
        "**Strength mod applies to damage at close range only."
      ],
      "name": "Dagger†‡",
      "costInCopper": 300.0
    },
    "tradeGood": {
      "name": "Ukulele",
      "costInCopper": 0.0
    }
  },
  {
    "name": "Noble",
    "startingWeapon": {
      "meleeDamage": "1d8",
      "wield": "ONE_HANDED",
      "type": "MELEE",
      "notes": [],
      "name": "Longsword",
      "costInCopper": 1000.0
    },
    "tradeGood": {
      "name": "Gold ring worth 10GP",
      "costInCopper": 0.0
    }
  },
  {
    "name": "Orphan",
    "startingWeapon": {
      "meleeDamage": "1d4",
      "wield": "ONE_HANDED",
      "type": "MELEE",
      "notes": [],
      "name": "Club",
      "costInCopper": 300.0
    },
    "tradeGood": {
      "name": "Rag doll",
      "costInCopper": 0.0
    }
  },
  {
    "name": "Ostler",
    "startingWeapon": {
      "meleeDamage": "1d4",
      "wield": "ONE_HANDED",
      "type": "MELEE",
      "notes": [],
      "name": "Staff",
      "costInCopper": 50.0
    },
    "tradeGood": {
      "notes": [],
      "name": "Bridle and Bit",
      "costInCopper": 200.0
    }
  },
  {
    "name": "Outlaw",
    "startingWeapon": {
      "meleeDamage": "1d6",
      "wield": "ONE_HANDED",
      "type": "MELEE",
      "notes": [],
      "name": "Short sword",
      "costInCopper": 700.0
    },
    "tradeGood": {
      "name": "Leather armor (equipped)",
      "costInCopper": 0.0
    }
  },
  {
    "name": "Rope maker",
    "startingWeapon": {
      "meleeDamage": "1d4",
      "rangedDamage": "1d10",
      "range": "10/20/30**",
      "wield": "ONE_HANDED",
      "type": "BOTH",
      "notes": [
        "† Thieves, when backstabbing, use the 2nd damage value, all others use the 1st.",
        "‡Chaotic chars use ceremonial daggers known as Athame, Kris, or Tumi.",
        "**Strength mod applies to damage at close range only."
      ],
      "name": "Knife (as dagger)",
      "costInCopper": 300.0
    },
    "tradeGood": {
      "name": "Rope, 100'",
      "costInCopper": 0.0
    }
  },
  {
    "name": "Scribe",
    "startingWeapon": {
      "range": "20/40/60**",
      "rangedDamage": "1d4",
      "wield": "ONE_HANDED",
      "type": "RANGED",
      "notes": [
        "**Strength mod applies to damage at close range only."
      ],
      "name": "Dart",
      "costInCopper": 50.0
    },
    "tradeGood": {
      "name": "Parchment, 10 sheets",
      "costInCopper": 0.0
    }
  },
  {
    "name": "Shaman",
    "startingWeapon": {
      "meleeDamage": "1d6",
      "wield": "ONE_HANDED",
      "type": "MELEE",
      "notes": [],
      "name": "Mace",
      "costInCopper": 500.0
    },
    "tradeGood": {
      "name": "Herbs, 1 lb.",
      "costInCopper": 0.0
    }
  },
  {
    "name": "Slave",
    "startingWeapon": {
      "meleeDamage": "1d4",
      "wield": "ONE_HANDED",
      "type": "MELEE",
      "notes": [],
      "name": "Club",
      "costInCopper": 300.0
    },
    "tradeGood": {
      "name": "Strange-looking rock",
      "costInCopper": 0.0
    }
  },
  {
    "name": "Smuggler",
    "startingWeapon": {
      "range": "40/80/160**",
      "rangedDamage": "1d4",
      "wield": "ONE_HANDED",
      "type": "RANGED",
      "notes": [
        "**Strength mod applies to damage at close range only."
      ],
      "name": "Sling",
      "costInCopper": 200.0
    },
    "tradeGood": {
      "name": "Waterproof sack",
      "costInCopper": 0.0
    }
  },
  {
    "name": "Soldier",
    "startingWeapon": {
      "meleeDamage": "1d8",
      "wield": "ONE_HANDED",
      "type": "MELEE",
      "notes": [
        "#These weapons inflict 2x damage on a mounted charge."
      ],
      "name": "Spear#",
      "costInCopper": 300.0
    },
    "tradeGood": {
      "name": "Shield (equipped)",
      "costInCopper": 0.0
    }
  },
  {
    "name": "Squire",
    "startingWeapon": {
      "meleeDamage": "1d8",
      "wield": "ONE_HANDED",
      "type": "MELEE",
      "notes": [],
      "name": "Longsword",
      "costInCopper": 1000.0
    },
    "tradeGood": {
      "name": "Steel helmet",
      "costInCopper": 0.0
    }
  },
  {
    "name": "Tax collector",
    "startingWeapon": {
      "meleeDamage": "1d8",
      "wield": "ONE_HANDED",
      "type": "MELEE",
      "notes": [],
      "name": "Longsword",
      "costInCopper": 1000.0
    },
    "tradeGood": {
      "name": "100CP",
      "costInCopper": 0.0
    }
  },
  {
    "name": "Trapper",
    "startingWeapon": {
      "range": "40/80/160**",
      "rangedDamage": "1d4",
      "wield": "ONE_HANDED",
      "type": "RANGED",
      "notes": [
        "**Strength mod applies to damage at close range only."
      ],
      "name": "Sling",
      "costInCopper": 200.0
    },
    "tradeGood": {
      "name": "Badger pelt",
      "costInCopper": 0.0
    }
  },
  {
    "name": "Urchin",
    "startingWeapon": {
      "meleeDamage": "1d4",
      "wield": "ONE_HANDED",
      "type": "MELEE",
      "notes": [],
      "name": "Stick (as club)",
      "costInCopper": 300.0
    },
    "tradeGood": {
      "name": "Begging bowl",
      "costInCopper": 0.0
    }
  },
  {
    "name": "Wainwright",
    "startingWeapon": {
      "meleeDamage": "1d4",
      "wield": "ONE_HANDED",
      "type": "MELEE",
      "notes": [],
      "name": "Club",
      "costInCopper": 300.0
    }
  },
  {
    "name": "Weaver",
    "startingWeapon": {
      "meleeDamage": "1d4",
      "rangedDamage": "1d10",
      "range": "10/20/30**",
      "wield": "ONE_HANDED",
      "type": "BOTH",
      "notes": [
        "† Thieves, when backstabbing, use the 2nd damage value, all others use the 1st.",
        "‡Chaotic chars use ceremonial daggers known as Athame, Kris, or Tumi.",
        "**Strength mod applies to damage at close range only."
      ],
      "name": "Dagger†‡",
      "costInCopper": 300.0
    },
    "tradeGood": {
      "name": "Fine suit of clothes",
      "costInCopper": 0.0
    }
  },
  {
    "name": "Wizard's apprentice",
    "startingWeapon": {
      "meleeDamage": "1d4",
      "rangedDamage": "1d10",
      "range": "10/20/30**",
      "wield": "ONE_HANDED",
      "type": "BOTH",
      "notes": [
        "† Thieves, when backstabbing, use the 2nd damage value, all others use the 1st.",
        "‡Chaotic chars use ceremonial daggers known as Athame, Kris, or Tumi.",
        "**Strength mod applies to damage at close range only."
      ],
      "name": "Dagger†‡",
      "costInCopper": 300.0
    },
    "tradeGood": {
      "name": "Black grimoire",
      "costInCopper": 0.0
    }
  },
  {
    "name": "Woodcutter",
    "startingWeapon": {
      "meleeDamage": "1d6",
      "rangedDamage": "1d6",
      "range": "10/20/30**",
      "wield": "ONE_HANDED",
      "type": "BOTH",
      "notes": [
        "**Strength mod applies to damage at close range only."
      ],
      "name": "Handaxe",
      "costInCopper": 400.0
    },
    "tradeGood": {
      "name": "Bundle of wood",
      "costInCopper": 0.0
    }
  }
]